graph_part/__init__.py
graph_part/__main__.py
graph_part/api.py
graph_part/cli.py
graph_part/graph_part.py
graph_part/mmseqs_needle_combined_utils.py
graph_part/mmseqs_utils.py
graph_part/molecules.py
graph_part/needle_utils.py
graph_part/precomputed_utils.py
graph_part/train_val_test_split.py
graph_part/transformations.py
graph_part-1.0.2.data/scripts/mmseqs_fake_prefilter.sh
graph_part-1.0.2.dist-info/LICENSE
graph_part-1.0.2.dist-info/METADATA
graph_part-1.0.2.dist-info/WHEEL
graph_part-1.0.2.dist-info/entry_points.txt
graph_part-1.0.2.dist-info/top_level.txt
graph_part-1.0.2.dist-info/RECORD
