Metadata-Version: 2.1
Name: graph-part
Version: 1.0.2
Summary: Graph-based partitioning of biological sequence data
Home-page: https://github.com/graph-part/graph-part
Author: F. Teufel and M.H. Gislason
Requires-Python: >=3.6, <4
License-File: LICENSE
Requires-Dist: numpy (>=1.19.5)
Requires-Dist: networkx (>=2.5.1)
Requires-Dist: tqdm (>=4.62.3)
Requires-Dist: pandas (>=1.1.5)
